{
	"WindowTitle": "Project particles",
	"WindowSizeX": 1920,
  "WindowSizeY": 1080,
	"ParticleImage": "assets/particle.png",
	"Debug": true,
	"InitNumParticles": 100,
	"RandomSpawn": true,
	"SpawnX": 400,
	"SpawnY": 400,
	"SpawnRate": 10,
	"ColorRandom":true,
	"ColorRed": 0,
	"ColorGreen": 0,
	"ColorBlue":0,
	"MaxSpeed":5,
	"TypeSpeed": 0,
	"Gravity": false,
	"GravityCoefficient": 0,
	"AddLifeToParticle": true,
	"LifeRate": 100,
	"Margin": true,
	"MargeCoefficient":0,
	"Design": false,
	"OpacityRate": 0,
	"CursorCercle":false, 
	"CercleShape": true,
	"CercleRadius" : 400,
	"CercleSpeed":true,
	"RotationSpeed":10
}
